ten/__init__.py
tenlib/__init__.py
tenlib/cli.py
tenlib/config.py
tenlib/exception.py
tenlib/flow/__init__.py
tenlib/flow/console.py
tenlib/flow/messageformatter.py
tenlib/fs.py
tenlib/http.py
tenlib/logging.py
tenlib/shell.py
tenlib/struct/__init__.py
tenlib/struct/map.py
tenlib/struct/proxy.py
tenlib/struct/storable.py
tenlib/struct/table.py
tenlib/struct/xmldict.py
tenlib/transform/__init__.py
tenlib/transform/base64.py
tenlib/transform/case.py
tenlib/transform/color.py
tenlib/transform/csv.py
tenlib/transform/generic.py
tenlib/transform/hashing.py
tenlib/transform/hexa.py
tenlib/transform/html.py
tenlib/transform/js.py
tenlib/transform/json.py
tenlib/transform/php.py
tenlib/transform/qs.py
tenlib/transform/random.py
tenlib/transform/sql.py
tenlib/transform/table.py
tenlib/transform/url.py
tenlib/util/__init__.py
tenlib/util/misc.py
tenlib/util/watch.py
ten-0.1.8.dist-info/METADATA
ten-0.1.8.dist-info/WHEEL
ten-0.1.8.dist-info/entry_points.txt
ten-0.1.8.dist-info/RECORD
