Metadata-Version: 2.1
Name: ten
Version: 0.1.8
Summary: A (small) web exploit framework
Author: Charles "cfreal" Fol
Author-email: folcharles@gmail.com
Requires-Python: >=3.10,<4.0
Classifier: Programming Language :: Python :: 3
Classifier: Programming Language :: Python :: 3.10
Classifier: Programming Language :: Python :: 3.11
Requires-Dist: beautifulsoup4 (>=4.12.2,<5.0.0)
Requires-Dist: colorama (>=0.4.6,<0.5.0)
Requires-Dist: lxml (>=4.9.2)
Requires-Dist: pyyaml (>=6.0,<7.0)
Requires-Dist: requests (>=2.28.2,<3.0.0)
Requires-Dist: requests-toolbelt (>=0.1.10) ; python_version >= "3"
Requires-Dist: requests-toolbelt (>=1) ; python_version >= "3.11"
Requires-Dist: rich (>=13.3.4,<14.0.0)
